smcpp_pipeline/__init__.py
smcpp_pipeline/smcpp_pipeline.py
smcpp_pipeline-0.4.0.dist-info/LICENSE
smcpp_pipeline-0.4.0.dist-info/METADATA
smcpp_pipeline-0.4.0.dist-info/WHEEL
smcpp_pipeline-0.4.0.dist-info/top_level.txt
smcpp_pipeline-0.4.0.dist-info/RECORD
