Metadata-Version: 2.1
Name: smcpp_pipeline
Version: 0.4.0
Summary: A python pipeline for implementing smcpp package to decipher demographic history of populations
Author: Devashish Tripathi
Author-email: devashishtripathi697@gmail.com
Classifier: Programming Language :: Python :: 3
Classifier: License :: OSI Approved :: MIT License
Classifier: Operating System :: OS Independent
Requires-Python: >=3.6
License-File: LICENSE
Requires-Dist: numpy >=1.18.5
Requires-Dist: pandas >=1.0.5
